arxiv_auth/__init__.py
arxiv_auth/auth/__init__.py
arxiv_auth/auth/decorators.py
arxiv_auth/auth/exceptions.py
arxiv_auth/auth/middleware.py
arxiv_auth/auth/scopes.py
arxiv_auth/auth/sessions/__init__.py
arxiv_auth/auth/sessions/store.py
arxiv_auth/auth/sessions/tests/__init__.py
arxiv_auth/auth/sessions/tests/test_integration.py
arxiv_auth/auth/sessions/tests/test_unit.py
arxiv_auth/auth/tests/__init__.py
arxiv_auth/auth/tests/test_decorators.py
arxiv_auth/auth/tests/test_extension.py
arxiv_auth/auth/tests/test_middleware.py
arxiv_auth/auth/tests/test_tokens.py
arxiv_auth/auth/tokens.py
arxiv_auth/domain.py
arxiv_auth/factory.py
arxiv_auth/helpers.py
arxiv_auth/legacy/__init__.py
arxiv_auth/legacy/accounts.py
arxiv_auth/legacy/authenticate.py
arxiv_auth/legacy/cookies.py
arxiv_auth/legacy/endorsements.py
arxiv_auth/legacy/exceptions.py
arxiv_auth/legacy/models.py
arxiv_auth/legacy/passwords.py
arxiv_auth/legacy/sessions.py
arxiv_auth/legacy/tests/__init__.py
arxiv_auth/legacy/tests/test_accounts.py
arxiv_auth/legacy/tests/test_authenticate.py
arxiv_auth/legacy/tests/test_bootstrap.py
arxiv_auth/legacy/tests/test_endorsements.py
arxiv_auth/legacy/tests/test_passwords.py
arxiv_auth/legacy/tests/test_sessions.py
arxiv_auth/legacy/tests/test_util.py
arxiv_auth/legacy/tests/util.py
arxiv_auth/legacy/util.py
arxiv_auth/tests/__init__.py
arxiv_auth/tests/test_domain.py
arxiv_auth/tests/test_helpers.py
arxiv_auth-1.0.0rc3.dist-info/WHEEL
arxiv_auth-1.0.0rc3.dist-info/METADATA
arxiv_auth-1.0.0rc3.dist-info/RECORD
