Metadata-Version: 2.1
Name: arxiv-auth
Version: 1.0.0rc3
Summary: Auth libraries for arXiv.
Author: arxiv.org
Requires-Python: >=3.10,<4.0
Classifier: Programming Language :: Python :: 3
Classifier: Programming Language :: Python :: 3.10
Requires-Dist: arxiv-base (>=1.0.0a3)
Requires-Dist: flask
Requires-Dist: flask-sqlalchemy
Requires-Dist: mimesis
Requires-Dist: mysqlclient
Requires-Dist: pycountry
Requires-Dist: pydantic
Requires-Dist: pyjwt
Requires-Dist: python-dateutil
Requires-Dist: redis (==2.10.6)
Requires-Dist: redis-py-cluster (==1.3.6)
Requires-Dist: sqlalchemy
